CHANGELOG.txt
LICENCE.txt
MANIFEST.in
README.txt
setup.py
tanbasic/__init__.py
tantanbasic.egg-info/PKG-INFO
tantanbasic.egg-info/SOURCES.txt
tantanbasic.egg-info/dependency_links.txt
tantanbasic.egg-info/top_level.txt