Metadata-Version: 2.1
Name: tantanbasic
Version: 0.0.1
Summary: Day la test thu vien tinh toan 2 so
Home-page: UNKNOWN
Author: tantan
Author-email: tanxuantan16@gmail.com
License: MIT
Keywords: tantanbasic
Platform: UNKNOWN
Classifier: Development Status :: 5 - Production/Stable
Classifier: Intended Audience :: Education
Classifier: Operating System :: Microsoft :: Windows :: Windows 10
Classifier: License :: OSI Approved :: MIT License
Classifier: Programming Language :: Python :: 3
License-File: LICENCE.txt
